<?xml version="1.0" encoding="UTF-8"?>
<dataset>
    <TB_CREDOR id="1" nome="Fulano" cpf="112.123.123-33" telefone="99988-6565" email="fulano@gmail.com" />
    <TB_CREDOR id="2" nome="Beltrano" cpf="332.321.321-11" telefone="98881-0001" email="beltrano@gmail.com" />

    <TB_DEVEDOR id="1" nome="Joao" cpf="665.654.654-44" />
    <TB_DEVEDOR id="2" nome="Paulo" cpf="998.987.987-77" />

    <TB_GUIA id="1" numero="20180001" data="09-02-2018 18:20:00" valor="73.20" />
    <TB_GUIA id="2" numero="20180002" data="09-02-2018 18:25:00" valor="160.85" />

    <TB_TITULO id="1" natureza="Protesto de pessoa fisica" valor="1500.00" />
    <TB_TITULO id="2" natureza="Protesto de pessoa fisica" valor="2700.00" />
</dataset>